thalas/__init__.py
thalas-0.0.0.dist-info/METADATA
thalas-0.0.0.dist-info/WHEEL
thalas-0.0.0.dist-info/top_level.txt
thalas-0.0.0.dist-info/RECORD
