Metadata-Version: 2.4
Name: thalas
Version: 0.0.0
Summary: Ray-based executor (factored from marin-community/marin)
Project-URL: Repository, https://github.com/marin-community/thalas
Requires-Python: >=3.10
